client.py
encrypt.py
publish.py
subscribe.py
yalgaar.py
pyYalgaar-1.0.6.dist-info/METADATA
pyYalgaar-1.0.6.dist-info/WHEEL
pyYalgaar-1.0.6.dist-info/top_level.txt
pyYalgaar-1.0.6.dist-info/RECORD
