Metadata-Version: 2.1
Name: pyYalgaar
Version: 1.0.6
Summary: This is yalgaar python SDK
Home-page: http://www.yalgaar.io
Author: Yalgaar
Author-email: yalgaar@slscorp.com
License: MIT
Keywords: Connecting to the yalgaar cloud
Platform: Posix; MacOS X; Windows
Classifier: Development Status :: 3 - Alpha
Classifier: Intended Audience :: Developers
Classifier: Topic :: Software Development :: Build Tools
Classifier: License :: OSI Approved :: MIT License
Classifier: Programming Language :: Python :: 3
Classifier: Programming Language :: Python :: 3.3
Classifier: Programming Language :: Python :: 3.4
Classifier: Programming Language :: Python :: 3.5
Requires-Dist: pycryptodome (==3.4)
